Workbook

Sheet Титул
A4: Реестр оценки влияния НПА и отраслевых событий
A5: Обновление за период 03–28.08.2026 · версия от 28.08.2026 · добавлены карточки № 44–46 (законопроект об обязательной маркировке ИИ-контента — внесён в ГД 17.08.2026; обновление проверочного листа Роскомнадзора по ПД; предложение Ассоциации больших данных о PETs-обработке ПД для обучения ИИ)
A7: Вкладка | C7: Содержание
A8: НПА | C8: Утверждённые и действующие документы: федеральные законы (№ 243-ФЗ, № 279-ФЗ, № 295-ФЗ, № 296-ФЗ), действующие сервисы и пилоты. Оценка по методике К1–К6.
A9: Проекты и анонсы | C9: Законопроекты, проекты НПА на публичном обсуждении, поручения и анонсы мер. При утверждении документа карточка переносится на лист «НПА».
A10: Отраслевые новости | C10: Рыночные события и судебная практика. Отдельное ранжирование — индекс актуальности (Н1–Н4: актуальность, релевантность GS Labs, масштаб, динамика).
A11: Методика | C11: Критерии К1–К6 и веса, шкала ИВ и категории, правила эскалации; методика индекса актуальности для новостей.
A12: Источники | C12: Источники, использованные при обновлении реестра за период.
A13: Ссылки мониторинга | C13: Каналы регулярного мониторинга (Telegram, дайджесты).
A15: Легенда
B16: ТРЕБУЕТ ОБНОВЛЕНИЯ — изменилась стадия/реквизиты акта, внесите правки в карточку
B17: Уточнение фактуры по существующей карточке (новые данные, сроки)
B18: Новая карточка, добавленная при текущем обновлении (на этой версии — 25–28.08.2026)
B19: Ячейки, заполняемые вручную (стадия, баллы, флаг эскалации, действия, сроки)
A21: Нумерация карточек сквозная (1–46) и сохранена от исходного реестра для трассируемости. Фильтры настроены на каждом листе (строка заголовков).

Sheet НПА
A1: GS Labs · Реестр оценки влияния — НПА (утверждённые документы)
A2: Утверждённые и действующие акты. Фильтры в строке заголовков; светло-зелёные ячейки — заполняемые вручную. Методика — одноимённый лист.
A3: № | B3: Идентификатор акта | C3: Тип документа | D3: Стадия акта | E3: Источник | F3: К1 Применимость (0–3) | G3: К2 Юр. сила (0–3) | H3: К3 Финансы (0–3) | I3: К4 Опер. сложность (0–3) | J3: К5 Юр./репутац. риск (0–3) | K3: К6 Срочность (0–3) | L3: Итоговый индекс (0–100) | M3: Категория (по индексу) | N3: Флаг эскалации | O3: Итоговая категория | P3: Суть / содержание
A4: 2 | B4: О поддержке развития технологий ИИ в РФ (ФЗ № 243-ФЗ) | C4: Федеральный закон | D4: Принят 26.07.2026, в силу с 01.09.2026 | E4: https://sozd.duma.gov.ru/bill/1271570-8 | F4: 3 | G4: 3 | H4: 1 | I4: 1 | J4: 0 | K4: 0 | L4: =IF(COUNT(F4:K4)=0,"",ROUND(((F4*Методика!$B$4+G4*Методика!$B$5+H4*Методика!$B$6+I4*Методика!$B$7+J4*Методика!$B$8+K4*Методика!$B$9)/3)*100,1)) -> 51.7 | M4: =IF(L4="","",INDEX(Методика!$C$15:$C$19,MATCH(L4,Методика!$A$15:$A$19,1))) -> Среднее | N4: Нет | O4: =IF(M4="","",IF(N4="Да",IF(M4="Критическое","Критическое","Высокое"),M4)) -> Среднее | P4: ФЗ № 243-ФЗ от 26.07.2026: рамочное регулирование ИИ, режим для больших фундаментальных моделей (≥1 млрд параметров); маркировка ИИ-контента (ст. 9) и уведомление пользователей о правах на результат генерации (ст. 10) — с 01.03.2027; переходный период до 09.2032.
A5: 4 | B5: Упрощение закупочных процедур (ФЗ № 279-ФЗ, изм. в 44-ФЗ) | C5: Федеральный закон | D5: Принят 04.08.2026, в силу с 01.10.2026 | E5: http://duma.gov.ru/news/63938/ | F5: 3 | G5: 2 | H5: 2 | I5: 1 | J5: 1 | K5: 2 | L5: =IF(COUNT(F5:K5)=0,"",ROUND(((F5*Методика!$B$4+G5*Методика!$B$5+H5*Методика!$B$6+I5*Методика!$B$7+J5*Методика!$B$8+K5*Методика!$B$9)/3)*100,1)) -> 65 | M5: =IF(L5="","",INDEX(Методика!$C$15:$C$19,MATCH(L5,Методика!$A$15:$A$19,1))) -> Среднее | N5: Нет | O5: =IF(M5="","",IF(N5="Да",IF(M5="Критическое","Критическое","Высокое"),M5)) -> Среднее | P5: ФЗ № 279-ФЗ от 04.08.2026: лимит электронного запроса котировок повышен до 20 млн ₽ (норма до 31.12.2027), закупки у МСП/СОНКО — до 30 млн ₽ (с 01.01.2027), расширены основания изменения контрактов, сокращён срок согласования закупки у единственного поставщика.
A6: 14 | B6: Налоговая медиация для IT-отрасли (пилот ФНС) | C6: Пилот/сервис ФНС | D6: Действует | E6: https://palata-nk.ru/upload/pdf/%D0%A0%D0%B0%D1%81%D0%BF%D0%BE%D1%80%D | F6: 2 | G6: 2 | H6: 1 | I6: 1 | J6: 0 | K6: 0 | L6: =IF(COUNT(F6:K6)=0,"",ROUND(((F6*Методика!$B$4+G6*Методика!$B$5+H6*Методика!$B$6+I6*Методика!$B$7+J6*Методика!$B$8+K6*Методика!$B$9)/3)*100,1)) -> 38.3 | M6: =IF(L6="","",INDEX(Методика!$C$15:$C$19,MATCH(L6,Методика!$A$15:$A$19,1))) -> Низкое | N6: Нет | O6: =IF(M6="","",IF(N6="Да",IF(M6="Критическое","Критическое","Высокое"),M6)) -> Низкое | P6: Пилот ФНС: крупные ИТ-компании могут бесплатно привлекать независимого медиатора на досудебной стадии налогового спора.
A7: 16 | B7: ФЗ № 296-ФЗ — патентная охрана алгоритмов и интерфейсов программ | C7: Федеральный закон | D7: Принят 04.08.2026, в силу с 01.01.2027 | E7: https://mfd.ru/news/view/?id=2779850 | F7: 3 | G7: 3 | H7: 1 | I7: 1 | J7: 1 | K7: 1 | L7: =IF(COUNT(F7:K7)=0,"",ROUND(((F7*Методика!$B$4+G7*Методика!$B$5+H7*Методика!$B$6+I7*Методика!$B$7+J7*Методика!$B$8+K7*Методика!$B$9)/3)*100,1)) -> 60 | M7: =IF(L7="","",INDEX(Методика!$C$15:$C$19,MATCH(L7,Методика!$A$15:$A$19,1))) -> Среднее | N7: Нет | O7: =IF(M7="","",IF(N7="Да",IF(M7="Критическое","Критическое","Высокое"),M7)) -> Среднее | P7: Изменения в ГК РФ: изобретением/полезной моделью может быть признано техническое решение, реализуемое программным способом (алгоритмы); промышленным образцом — графический интерфейс программы (визуальное отображение для взаимодействия человека с программой).
A8: 17 | B8: ФЗ № 295-ФЗ — адм. ответственность за нарушения закона о платформенной экономике | C8: Федеральный закон (изм. в КоАП) | D8: Принят и подписан 04.08.2026 | E8: https://www.klerk.ru/cdoc/view/cdbcb718c9a27fad70e808103ccd965b/ | F8: 1 | G8: 3 | H8: 1 | I8: 1 | J8: 1 | K8: 2 | L8: =IF(COUNT(F8:K8)=0,"",ROUND(((F8*Методика!$B$4+G8*Методика!$B$5+H8*Методика!$B$6+I8*Методика!$B$7+J8*Методика!$B$8+K8*Методика!$B$9)/3)*100,1)) -> 46.7 | M8: =IF(L8="","",INDEX(Методика!$C$15:$C$19,MATCH(L8,Методика!$A$15:$A$19,1))) -> Низкое | N8: Нет | O8: =IF(M8="","",IF(N8="Да",IF(M8="Критическое","Критическое","Высокое"),M8)) -> Низкое | P8: КоАП дополнен составами о нарушениях ФЗ № 289-ФЗ о платформенной экономике (в силу с 01.10.2026): штрафы для операторов посреднических цифровых платформ до 500 тыс. ₽ — за дефекты карточек товаров, необоснованное ограничение доступа партнёров, нарушения поисковой выдачи и договорных требований.
A9: 22 | B9: Постановление Правительства № 402 от 13.04.2026 — отраслевые особенности категорирования КИИ в сфере связи | C9: Постановление Правительства | D9: Принято, в силу с 01.09.2026 | E9: https://passwork.ru/blog/importozamieshchieniie-kii-v-2026/. http://publication.pravo.gov.ru/document/0001202604130022 | F9: 3 | G9: 3 | H9: 2 | I9: 2 | J9: 1 | K9: 3 | L9: =IF(COUNT(F9:K9)=0,"",ROUND(((F9*Методика!$B$4+G9*Методика!$B$5+H9*Методика!$B$6+I9*Методика!$B$7+J9*Методика!$B$8+K9*Методика!$B$9)/3)*100,1)) -> 78.3 | M9: =IF(L9="","",INDEX(Методика!$C$15:$C$19,MATCH(L9,Методика!$A$15:$A$19,1))) -> Высокое | N9: Нет | O9: =IF(M9="","",IF(N9="Да",IF(M9="Критическое","Критическое","Высокое"),M9)) -> Высокое | P9: Первый отраслевой акт по 58-ФЗ: определяет отраслевые признаки значимости и порядок расчёта показателей критериев значимости для объектов КИИ в сфере связи. Системы условного доступа к телерадиовещанию уже включены в перечень типовых отраслевых объектов КИИ (распоряжение № 360-р от 26.02.2026).
A10: 23 | B10: Постановление Правительства № 1937 от 28.11.2025 — новые правила реестра российского ПО (совместимость с доверенными ОС) | C10: Постановление Правительства | D10: Действует с 01.03.2026; поэтапные требования с 01.09.2026 | E10: https://www.pgplaw.ru/analytics-and-brochures/alerts/pravila-vedeniya-reestra-rossiyskogo-po/ | F10: 3 | G10: 3 | H10: 2 | I10: 2 | J10: 1 | K10: 2 | L10: =IF(COUNT(F10:K10)=0,"",ROUND(((F10*Методика!$B$4+G10*Методика!$B$5+H10*Методика!$B$6+I10*Методика!$B$7+J10*Методика!$B$8+K10*Методика!$B$9)/3)*100,1)) -> 75 | M10: =IF(L10="","",INDEX(Методика!$C$15:$C$19,MATCH(L10,Методика!$A$15:$A$19,1))) -> Высокое | N10: Нет | O10: =IF(M10="","",IF(N10="Да",IF(M10="Критическое","Критическое","Высокое"),M10)) -> Высокое | P10: Обязательная совместимость включённого в реестр ПО минимум с двумя доверенными российскими ОС: с 01.09.2026 — офисное ПО; с 01.01.2027 — серверное, СУБД, средства разработки, виртуализация, мониторинг; с 01.06.2027 — прикладное и отраслевое ПО, средства ИБ; с 01.01.2028 — промышленное. Ежегодное обновление сведений до 1 июня; отметка о доверенном ПО — преимущество в закупках 44-ФЗ/223-ФЗ.
A11: 37 | B11: Указ Президента РФ от 24.08.2026 № 604 «О мерах по обеспечению безопасности объектов критической инфраструктуры РФ» | C11: Указ Президента (подписан, действует) | D11: Подписан и опубликован 24.08.2026; в силу со дня официального опубликования | E11: https://www.garant.ru/hotlaw/federal/2212104/ | F11: 1 | G11: 3 | H11: 1 | I11: 1 | J11: 1 | K11: 3 | L11: =IF(COUNT(F11:K11)=0,"",ROUND(((F11*Методика!$B$4+G11*Методика!$B$5+H11*Методика!$B$6+I11*Методика!$B$7+J11*Методика!$B$8+K11*Методика!$B$9)/3)*100,1)) -> 50 | M11: =IF(L11="","",INDEX(Методика!$C$15:$C$19,MATCH(L11,Методика!$A$15:$A$19,1))) -> Среднее | N11: Нет | O11: =IF(M11="","",IF(N11="Да",IF(M11="Критическое","Критическое","Высокое"),M11)) -> Среднее | P11: При непринятии/несвоевременном принятии хозяйствующим субъектом мер по обеспечению безопасности объектов критической инфраструктуры (в т.ч. неэффективности мер против атак БПЛА, несвоевременном восстановлении работы) по решению Правительства на основании поручения Президента вводится временное управление имуществом, ценными бумагами/долями и имущественными правами владельца. Временный управляющий — Росимущество (или иное лицо по решению Правительства); полномочия собственника без права распоряжения. Под объектами КИ — объекты ТЭК, промышленные объекты, объекты связи, коммунальной, транспортной, логистической инфраструктуры, энергетики (вкл. атомную), жизнеобеспечения, критически важные и потенциально опасные объекты. Принят «в связи с нарастанием угроз безопасности объектов КИ в период СВО».

Sheet Проекты и анонсы
A1: GS Labs · Реестр оценки влияния — Проекты НПА и анонсы
A2: Законопроекты, проекты НПА на обсуждении, поручения и анонсы мер. При изменении стадии документа переносите карточку на лист «НПА» и переоцените К2.
A3: № | B3: Идентификатор акта | C3: Тип документа | D3: Стадия акта | E3: Источник | F3: К1 Применимость (0–3) | G3: К2 Юр. сила (0–3) | H3: К3 Финансы (0–3) | I3: К4 Опер. сложность (0–3) | J3: К5 Юр./репутац. риск (0–3) | K3: К6 Срочность (0–3) | L3: Итоговый индекс (0–100) | M3: Категория (по индексу) | N3: Флаг эскалации | O3: Итоговая категория | P3: Суть / содержание
A4: 1 | B4: Законопроект CAS DRM (№ 1215252-8) | C4: Законопроект (внесён в ГД) | D4: Законопроект внесён, I чтение — осенняя сессия 2026 | E4: https://sozd.duma.gov.ru/bill/1215252-8 | F4: 3 | G4: 2 | H4: 3 | I4: 0 | J4: 0 | K4: 3 | L4: =IF(COUNT(F4:K4)=0,"",ROUND(((F4*Методика!$B$4+G4*Методика!$B$5+H4*Методика!$B$6+I4*Методика!$B$7+J4*Методика!$B$8+K4*Методика!$B$9)/3)*100,1)) -> 65 | M4: =IF(L4="","",INDEX(Методика!$C$15:$C$19,MATCH(L4,Методика!$A$15:$A$19,1))) -> Среднее | N4: Да | O4: =IF(M4="","",IF(N4="Да",IF(M4="Критическое","Критическое","Высокое"),M4)) -> Высокое | P4: Обязательный переход операторов платного ТВ, вещателей и аудиовизуальных сервисов на системы условного доступа и DRM из реестра российского ПО с 01.01.2027; при исключении используемой системы из реестра — 6 месяцев на замену и перевод абонентов.
A5: 5 | B5: Разработаны показатели по внедрению ИИ для всех отраслей экономики | C5: Анонс (показатели Правительства) | D5: Анонс | E5: http://government.ru/news/59344/ | F5: 3 | G5: 2 | H5: 1 | I5: 2 | J5: 1 | K5: 1 | L5: =IF(COUNT(F5:K5)=0,"",ROUND(((F5*Методика!$B$4+G5*Методика!$B$5+H5*Методика!$B$6+I5*Методика!$B$7+J5*Методика!$B$8+K5*Методика!$B$9)/3)*100,1)) -> 60 | M5: =IF(L5="","",INDEX(Методика!$C$15:$C$19,MATCH(L5,Методика!$A$15:$A$19,1))) -> Среднее | N5: Нет | O5: =IF(M5="","",IF(N5="Да",IF(M5="Критическое","Критическое","Высокое"),M5)) -> Среднее | P5: Правительство разработало систему показателей внедрения ИИ для отраслей экономики; при госзаказе на ИИ-продукты потребуется измеримый экономический эффект.
A6: 6 | B6: Меры поддержки от ФРП и «умный протекционизм» | C6: Анонс (меры поддержки) | D6: Анонс | E6: http://government.ru/news/59377/ | F6: 2 | G6: 1 | H6: 2 | I6: 2 | J6: 1 | K6: 1 | L6: =IF(COUNT(F6:K6)=0,"",ROUND(((F6*Методика!$B$4+G6*Методика!$B$5+H6*Методика!$B$6+I6*Методика!$B$7+J6*Методика!$B$8+K6*Методика!$B$9)/3)*100,1)) -> 53.3 | M6: =IF(L6="","",INDEX(Методика!$C$15:$C$19,MATCH(L6,Методика!$A$15:$A$19,1))) -> Среднее | N6: Нет | O6: =IF(M6="","",IF(N6="Да",IF(M6="Критическое","Критическое","Высокое"),M6)) -> Среднее | P6: Переориентация льготных займов ФРП под задачи нацпроектов технологического лидерства; «умный протекционизм»: запрет заёмщикам закупать импортное оборудование при наличии российского аналога, ставка 1% при покупке отечественных станков и роботов.
A7: 8 | B7: Налоговые льготы и поддержка для ИИ и ИТ-отрасли | C7: Анонс (налоговые меры) | D7: Анонс (обсуждение пакета) | E7: https://www.interfax.ru/business/1103270 | F7: 2 | G7: 1 | H7: 2 | I7: 1 | J7: 1 | K7: 1 | L7: =IF(COUNT(F7:K7)=0,"",ROUND(((F7*Методика!$B$4+G7*Методика!$B$5+H7*Методика!$B$6+I7*Методика!$B$7+J7*Методика!$B$8+K7*Методика!$B$9)/3)*100,1)) -> 48.3 | M7: =IF(L7="","",INDEX(Методика!$C$15:$C$19,MATCH(L7,Методика!$A$15:$A$19,1))) -> Низкое | N7: Нет | O7: =IF(M7="","",IF(N7="Да",IF(M7="Критическое","Критическое","Высокое"),M7)) -> Низкое | P7: Обсуждаемый пакет: повышающие коэффициенты к затратам на разработку и применение ИИ (включая покупку оборудования), спецамортизация ОС для ИИ, льготный НДС на услуги разработки ИИ и удалённого доступа к ИИ-платформам, расширение ИТ-льгот на компании, внедряющие ИИ.
A8: 9 | B8: ГСС и КБ (законопроект о Государственной системе связи) | C8: Проект закона (regulation.gov.ru) | D8: Проект НПА на обсуждении | E8: https://regulation.gov.ru/projects/162556/ | F8: 2 | G8: 1 | H8: 1 | I8: 1 | J8: 0 | K8: 1 | L8: =IF(COUNT(F8:K8)=0,"",ROUND(((F8*Методика!$B$4+G8*Методика!$B$5+H8*Методика!$B$6+I8*Методика!$B$7+J8*Методика!$B$8+K8*Методика!$B$9)/3)*100,1)) -> 36.7 | M8: =IF(L8="","",INDEX(Методика!$C$15:$C$19,MATCH(L8,Методика!$A$15:$A$19,1))) -> Низкое | N8: Нет | O8: =IF(M8="","",IF(N8="Да",IF(M8="Критическое","Критическое","Высокое"),M8)) -> Низкое | P8: Вводится правовое регулирование Государственной системы связи (ГСС), определяются категории пользователей (госорганы и субъекты КИИ), усиливается контроль.
A9: 10 | B9: Доктрина противодействия правонарушениям с использованием ИКТ (2027–2035) | C9: Стратегический документ (доктрина) | D9: Доктрина (направлена на реализацию) | E9: https://digital.gov.ru/documents/doktrina-razvitiya-sistemy-protivodej | F9: 2 | G9: 1 | H9: 2 | I9: 1 | J9: 0 | K9: 1 | L9: =IF(COUNT(F9:K9)=0,"",ROUND(((F9*Методика!$B$4+G9*Методика!$B$5+H9*Методика!$B$6+I9*Методика!$B$7+J9*Методика!$B$8+K9*Методика!$B$9)/3)*100,1)) -> 43.3 | M9: =IF(L9="","",INDEX(Методика!$C$15:$C$19,MATCH(L9,Методика!$A$15:$A$19,1))) -> Низкое | N9: Нет | O9: =IF(M9="","",IF(N9="Да",IF(M9="Критическое","Критическое","Высокое"),M9)) -> Низкое | P9: Доктрина на 2027–2035 гг.: цели по борьбе с киберпреступностью, сокращению оборота ПД, развитию государственно-частного партнёрства, подготовке кадров.
A10: 12 | B10: Проект приказа ФСТЭК «О защите ПД» | C10: Проект приказа (ФСТЭК) | D10: Обсуждение завершено 08.08.2026; в силу с 01.09.2026 | E10: https://regulation.gov.ru/projects/169583/ | F10: 3 | G10: 1 | H10: 2 | I10: 2 | J10: 2 | K10: 2 | L10: =IF(COUNT(F10:K10)=0,"",ROUND(((F10*Методика!$B$4+G10*Методика!$B$5+H10*Методика!$B$6+I10*Методика!$B$7+J10*Методика!$B$8+K10*Методика!$B$9)/3)*100,1)) -> 70 | M10: =IF(L10="","",INDEX(Методика!$C$15:$C$19,MATCH(L10,Методика!$A$15:$A$19,1))) -> Среднее | N10: Да | O10: =IF(M10="","",IF(N10="Да",IF(M10="Критическое","Критическое","Высокое"),M10)) -> Высокое | P10: Проект приказа ФСТЭК (замена приказа № 21): риск-ориентированная модель мер защиты, блок защиты ПД при использовании ИИ, обязательная оценка уровня зрелости (до начала обработки, не реже 1 раза в 3 года, после инцидентов), требования к подрядчикам, взаимодействие с ГосСОПКА.
A11: 13 | B11: Проект ГОСТ Р «Безопасная разработка ПО с использованием ИИ» (ТК 362) | C11: Проект стандарта (ГОСТ Р) | D11: Публичное обсуждение до 17.09.2026 | E11: https://fstec.ru/tk-362/standarty/proekty/proekt-natsionalnogo-standar | F11: 3 | G11: 1 | H11: 1 | I11: 2 | J11: 1 | K11: 1 | L11: =IF(COUNT(F11:K11)=0,"",ROUND(((F11*Методика!$B$4+G11*Методика!$B$5+H11*Методика!$B$6+I11*Методика!$B$7+J11*Методика!$B$8+K11*Методика!$B$9)/3)*100,1)) -> 55 | M11: =IF(L11="","",INDEX(Методика!$C$15:$C$19,MATCH(L11,Методика!$A$15:$A$19,1))) -> Среднее | N11: Да | O11: =IF(M11="","",IF(N11="Да",IF(M11="Критическое","Критическое","Высокое"),M11)) -> Высокое | P11: Проект стандарта ТК 362: единые требования к безопасной разработке ИИ-систем — ППК (машиночитаемый перечень программных компонентов), управление датасетами, защита от отравления данных, контроль цепочек поставок данных и моделей, локализация инфраструктуры обучения в РФ.
A12: 15 | B12: Законопроект о едином тарифе страховых взносов для IT (7,6%) (№ 1286413-8) | C12: Законопроект (внесён в ГД) | D12: Внесён 10.07.2026, I чтение не назначено | E12: https://sozd.duma.gov.ru/bill/1286413-8 | F12: 3 | G12: 1 | H12: 3 | I12: 1 | J12: 0 | K12: 1 | L12: =IF(COUNT(F12:K12)=0,"",ROUND(((F12*Методика!$B$4+G12*Методика!$B$5+H12*Методика!$B$6+I12*Методика!$B$7+J12*Методика!$B$8+K12*Методика!$B$9)/3)*100,1)) -> 58.3 | M12: =IF(L12="","",INDEX(Методика!$C$15:$C$19,MATCH(L12,Методика!$A$15:$A$19,1))) -> Среднее | N12: Нет | O12: =IF(M12="","",IF(N12="Да",IF(M12="Критическое","Критическое","Высокое"),M12)) -> Среднее | P12: Предлагается единый тариф 30% для всех выплат (вместо регрессивной шкалы) и единый пониженный тариф 7,6% для ИТ-компаний, НКО и резидентов ОЭЗ — без привязки к предельной базе.
A13: 18 | B13: Проект постановления о предустановке ИИ «системных помощников» на устройства (Минцифры) | C13: Проект постановления Правительства | D13: Публичное обсуждение (с 03.08.2026) | E13: https://www.cnews.ru/news/top/2026-08-04_v_rossii_vvodyat_obyazatelnuyu | F13: 2 | G13: 1 | H13: 1 | I13: 2 | J13: 0 | K13: 1 | L13: =IF(COUNT(F13:K13)=0,"",ROUND(((F13*Методика!$B$4+G13*Методика!$B$5+H13*Методика!$B$6+I13*Методика!$B$7+J13*Методика!$B$8+K13*Методика!$B$9)/3)*100,1)) -> 41.7 | M13: =IF(L13="","",INDEX(Методика!$C$15:$C$19,MATCH(L13,Методика!$A$15:$A$19,1))) -> Низкое | N13: Нет | O13: =IF(M13="","",IF(N13="Да",IF(M13="Критическое","Критическое","Высокое"),M13)) -> Низкое | P13: Новый класс предустанавливаемого ПО — «системный помощник» на базе ИИ: обязательный экран выбора при первом включении устройства, возможность отказа, равные условия для всех сервисов из перечня, бесплатная предустановленная версия.
A14: 19 | B14: «Антифрод 3.0»: единая платформа управления согласиями на обработку ПД (Минцифры) | C14: Пакет мер (обсуждение) | D14: Обсуждение (не внесён в ГД) | E14: https://www.kommersant.ru/doc/8861657 | F14: 2 | G14: 1 | H14: 2 | I14: 2 | J14: 1 | K14: 0 | L14: =IF(COUNT(F14:K14)=0,"",ROUND(((F14*Методика!$B$4+G14*Методика!$B$5+H14*Методика!$B$6+I14*Методика!$B$7+J14*Методика!$B$8+K14*Методика!$B$9)/3)*100,1)) -> 50 | M14: =IF(L14="","",INDEX(Методика!$C$15:$C$19,MATCH(L14,Методика!$A$15:$A$19,1))) -> Среднее | N14: Нет | O14: =IF(M14="","",IF(N14="Да",IF(M14="Критическое","Критическое","Высокое"),M14)) -> Среднее | P14: Третий антифрод-пакет: единая платформа управления согласиями граждан на обработку ПД — все 2,6 млн операторов должны будут передавать сведения о согласиях; граждане смогут отзывать их «в одном окне». Против — ЦБ и Минэкономразвития; бизнес оценивает переходный период в 12–18 мес.
A15: 20 | B15: Поручения Правительства по итогам ЦИПР-2026 (гранты до 80%, приоритет российского ИИ, УСН для ИТ) | C15: Поручения Правительства | D15: Анонс (предложения до 20.12.2026) | E15: https://rg.ru/2026/08/08/mishustin-poruchil-uvelichit-granty-na-vnedrenie-otechestvennogo-softa-do-80.html | F15: 3 | G15: 1 | H15: 2 | I15: 1 | J15: 0 | K15: 1 | L15: =IF(COUNT(F15:K15)=0,"",ROUND(((F15*Методика!$B$4+G15*Методика!$B$5+H15*Методика!$B$6+I15*Методика!$B$7+J15*Методика!$B$8+K15*Методика!$B$9)/3)*100,1)) -> 51.7 | M15: =IF(L15="","",INDEX(Методика!$C$15:$C$19,MATCH(L15,Методика!$A$15:$A$19,1))) -> Среднее | N15: Нет | O15: =IF(M15="","",IF(N15="Да",IF(M15="Критическое","Критическое","Высокое"),M15)) -> Среднее | P15: Поручения по итогам ЦИПР-2026: рост грантового софинансирования особо значимых ИТ-проектов с 50% до 80%; приоритет отечественных ИИ-решений в госзакупках; региональные ставки УСН для ИТ ≤3%/≤8% (до 01.12.2026); ускоренный перевод объектов КИИ на российское ПО; сводный доклад до 01.09.2026.
... A26: 46 | B26: Предложение Ассоциации больших данных: обработка ПД с применением PETs без согласий для обучения ИИ (институт доверенного посредника) | C26: Инициатива (письмо в Минцифры) | D26: Письмо АБД в Минцифры от 03.08.2026; обсуждение | E26: https://www.kommersant.ru/doc/8863449 | F26: 2 | G26: 2 | H26: 1 | I26: 1 | J26: 1 | K26: 1 | L26: =IF(COUNT(F26:K26)=0,"",ROUND(((F26*Методика!$B$4+G26*Методика!$B$5+H26*Методика!$B$6+I26*Методика!$B$7+J26*Методика!$B$8+K26*Методика!$B$9)/3)*100,1)) -> 46.7 | M26: =IF(L26="","",INDEX(Методика!$C$15:$C$19,MATCH(L26,Методика!$A$15:$A$19,1))) -> Низкое | N26: Нет | O26: =IF(M26="","",IF(N26="Да",IF(M26="Критическое","Критическое","Высокое"),M26)) -> Низкое | P26: Ассоциация больших данных (Авито, Сбер, Ростелеком, Яндекс, HH, VK) предложила Минцифры разрешить обработку персональных данных без согласий субъектов для обучения ИИ-моделей при условии применения технологий конфиденциальных вычислений (PETs) и участия «доверенного посредника». Цель — снять дефицит легальных данных для обучения суверенных ИИ

Sheet Отраслевые новости
A1: GS Labs · Отраслевые новости и судебная практика — ранжирование по актуальности
A2: Ранжирование по индексу актуальности (Н1–Н4), а не по методике НПА: шкала и веса — лист «Методика», блок с строки 31.
A3: № | B3: Событие | C3: Тип | D3: Дата / период | E3: Источник | F3: Н1 Актуальность (0–3) | G3: Н2 Релевантность GS Labs (0–3) | H3: Н3 Масштаб для отрасли (0–3) | I3: Н4 Динамика развития (0–3) | J3: Индекс актуальности (0–100) | K3: Категория актуальности | L3: Суть события
A4: 3 | B4: Кризис рынка ЦОД | C4: Рыночные данные | D4: 06.08.2026 (данные II кв. 2026) | E4: https://telesputnik.ru/materials/trends/news/rossiiskii-rynok-cod-stol | F4: 3 | G4: 2 | H4: 3 | I4: 2 | J4: =IF(COUNT(F4:I4)=0,"",ROUND(((F4*Методика!$B$33+G4*Методика!$B$34+H4*Методика!$B$35+I4*Методика!$B$36)/3)*100,1)) -> 83.3 | K4: =IF(J4="","",INDEX(Методика!$C$42:$C$45,MATCH(J4,Методика!$A$42:$A$45,1))) -> Горячая тема | L4: Дефицит мощностей ЦОД в Москве и СПб: сроки подключения 2–5 лет, фактический запрет на новые техусловия в Москве. II кв. 2026: стойка 5 кВт — 170,8 тыс. ₽ (+15,7% г/г) в Москве, 138 тыс. ₽ (+31,3%) в СПб; стойки 15–20 кВт под ИИ сокращают ёмкость машзалов.
A5: 7 | B5: Бюро 1440, развертывание низкоорбитального интернета | C5: Технологическое событие | D5: 19.07.2026 (запуск), обновление 04.08.2026 | E5: https://digital.gov.ru/news/vtoraya-partiya-sputnikov-rossijskoj-nizko | F5: 2 | G5: 2 | H5: 2 | I5: 2 | J5: =IF(COUNT(F5:I5)=0,"",ROUND(((F5*Методика!$B$33+G5*Методика!$B$34+H5*Методика!$B$35+I5*Методика!$B$36)/3)*100,1)) -> 66.7 | K5: =IF(J5="","",INDEX(Методика!$C$42:$C$45,MATCH(J5,Методика!$A$42:$A$45,1))) -> Актуально | L5: Развёртывание низкоорбитальной группировки «Рассвет-3»: 19.07.2026 выведена вторая партия из 16 спутников (опорная орбита 287–325 км, наклонение 82,3°), идут регламентные работы и подготовка первых клиентских тестов; до конца 2026 г. запланировано ещё 7 пусков (цель — 156 аппаратов).
A6: 11 | B6: Разглашение КТ через ИИ-сервисы (судебная практика) | C6: Судебная практика | D6: 2026 | E6: https://mos-gorsud.ru/rs/babushkinskij/services/cases/civil/details/73 | F6: 2 | G6: 3 | H6: 2 | I6: 1 | J6: =IF(COUNT(F6:I6)=0,"",ROUND(((F6*Методика!$B$33+G6*Методика!$B$34+H6*Методика!$B$35+I6*Методика!$B$36)/3)*100,1)) -> 70 | K6: =IF(J6="","",INDEX(Методика!$C$42:$C$45,MATCH(J6,Методика!$A$42:$A$45,1))) -> Актуально | L6: Загрузка рабочих данных (в т.ч. агрегированных отчётов) в публичные ИИ-сервисы признана судом разглашением коммерческой тайны — даже без доказательства факта утечки.
A7: 28 | B7: Аудитория онлайн-кинотеатров превысила 72 млн подписчиков (TelecomDaily, II кв. 2026) | C7: Рыночные данные | D7: 05–06.08.2026 | E7: https://telecomdaily.ru/news/2026/08/05/iaa-telecomdaily-chislo-podpischikov-ok-v-rossii-prevysilo-72-mln | F7: 3 | G7: 3 | H7: 2 | I7: 2 | J7: =IF(COUNT(F7:I7)=0,"",ROUND(((F7*Методика!$B$33+G7*Методика!$B$34+H7*Методика!$B$35+I7*Методика!$B$36)/3)*100,1)) -> 86.7 | K7: =IF(J7="","",INDEX(Методика!$C$42:$C$45,MATCH(J7,Методика!$A$42:$A$45,1))) -> Горячая тема | L7: По итогам II кв. 2026 г. более 72 млн пользователей в России являлись подписчиками девяти ведущих онлайн-кинотеатров; рынок легальных видеосервисов в 2025 г. вырос на 29,2% до 220,1 млрд ₽.
A8: 29 | B8: Принят закон о штрафах УК до 500 тыс. ₽ за воспрепятствование доступу операторов связи в МКД; отрасль обсуждает «реформу связи» | C8: Отраслевое событие | D8: 07.08.2026 | E8: https://www.cableman.ru/ | F8: 2 | G8: 1 | H8: 2 | I8: 1 | J8: =IF(COUNT(F8:I8)=0,"",ROUND(((F8*Методика!$B$33+G8*Методика!$B$34+H8*Методика!$B$35+I8*Методика!$B$36)/3)*100,1)) -> 50 | K8: =IF(J8="","",INDEX(Методика!$C$42:$C$45,MATCH(J8,Методика!$A$42:$A$45,1))) -> Актуально | L8: Госдума приняла закон об административной ответственности управляющих компаний за нарушение правил взаимодействия с операторами связи (штрафы для юрлиц до 500 тыс. ₽); одновременно отрасль дискутирует о параметрах грядущей «реформы связи» и её влиянии на экономику провайдеров.
A9: 33 | B9: ФАС возбудила дело против Apple из-за отсутствия предустановки MAX и RuStore на iPhone/iPad | C9: Отраслевое событие (анонс регуляторного действия) | D9: конец июля — август 2026 | E9: https://ebrlaw.ru/ | F9: 3 | G9: 2 | H9: 2 | I9: 2 | J9: =IF(COUNT(F9:I9)=0,"",ROUND(((F9*Методика!$B$33+G9*Методика!$B$34+H9*Методика!$B$35+I9*Методика!$B$36)/3)*100,1)) -> 76.7 | K9: =IF(J9="","",INDEX(Методика!$C$42:$C$45,MATCH(J9,Методика!$A$42:$A$45,1))) -> Горячая тема | L9: ФАС возбудила дело в отношении Apple: не исполнено предупреждение о предустановке отечественного магазина RuStore и нацмессенджера MAX (предупреждение выдано в начале июля, срок исполнения — 15.07; с 27.07 реализована только предустановка российской поисковой системы). Предварительная оценка максимального штрафа — до 4 млрд ₽.
A10: 34 | B10: Пресненский суд: изображения, созданные генеративным ИИ, не охраняются авторским правом (дело Позднякова) | C10: Судебная практика | D10: июль 2026 | E10: https://ebrlaw.ru/ | F10: 2 | G10: 3 | H10: 2 | I10: 2 | J10: =IF(COUNT(F10:I10)=0,"",ROUND(((F10*Методика!$B$33+G10*Методика!$B$34+H10*Методика!$B$35+I10*Методика!$B$36)/3)*100,1)) -> 76.7 | K10: =IF(J10="","",INDEX(Методика!$C$42:$C$45,MATCH(J10,Методика!$A$42:$A$45,1))) -> Горячая тема | L10: Одно из первых развёрнутых решений о неохраноспособности результатов генеративного ИИ: формирование и уточнение промптов — технический, а не творческий характер; презумпция п. 80 Постановления Пленума ВС № 10 не освобождает от доказывания личного творческого вклада; общее заключение специалиста без указания конкретных творческих решений недостаточно (в иске отказано).
A11: 36 | B11: ЦТС (GS Group) выпустил 30-миллионную телевизионную приставку | C11: Корпоративное событие GS Group | D11: 12.08.2026 | E11: https://gs-group.com/press-center/news/ | F11: 3 | G11: 3 | H11: 2 | I11: 1 | J11: =IF(COUNT(F11:I11)=0,"",ROUND(((F11*Методика!$B$33+G11*Методика!$B$34+H11*Методика!$B$35+I11*Методика!$B$36)/3)*100,1)) -> 80 | K11: =IF(J11="","",INDEX(Методика!$C$42:$C$45,MATCH(J11,Методика!$A$42:$A$45,1))) -> Горячая тема | L11: На площадке контрактного производства «Цифровые Телевизионные Системы» (Гусев, Калининградская обл., входит в GS Group) произведена 30-миллионная телевизионная приставка — юбилейный рубеж крупнейшего российского производства ТВ-оборудования.
A12: 41 | B12: Обсуждается переход к ОБЯЗАТЕЛЬНОЙ маркировке ИИ-контента (поправки рабочей группы Совета по кодификации) | C12: Регуляторная инициатива (проект поправок к закону об ИИ и ГК РФ) | D12: 12–20.08.2026; финальные предложения — конец сентября 2026 | E12: GR-дайджест 12–20.08.2026 (Телеспутник) | F12: 3 | G12: 3 | H12: 2 | I12: 3 | J12: =IF(COUNT(F12:I12)=0,"",ROUND(((F12*Методика!$B$33+G12*Методика!$B$34+H12*Методика!$B$35+I12*Методика!$B$36)/3)*100,1)) -> 93.3 | K12: =IF(J12="","",INDEX(Методика!$C$42:$C$45,MATCH(J12,Методика!$A$42:$A$45,1))) -> Горячая тема | L12: Рабочая группа Совета при Президенте по кодификации (П. Крашенинников) подготовила проект поправок к закону об ИИ и ГК РФ: обязательная маркировка аудиовизуального контента, созданного большими ИИ-моделями, вместо действующей добровольной схемы (платформы >500 тыс. пользователей лишь обязаны предоставлять техническую возможность маркировки). АИВ (А. Бырдин): редакция создаёт неопределённость — ключевые решения (ответственность, проверка при переносе файлов, порог использования ИИ) выносятся в подзаконные акты; альтернативы — китайская модель скрытых машиночитаемых меток, EU AI Act.
A13: 42 | B13: Совет по генеративной разработке ПО при Минцифры (инициатива «Сбера») | C13: Отраслевое событие (новая институциональная площадка) | D13: 12–20.08.2026; поручение Шадаева — предложения к концу 2026 | E13: GR-дайджест 12–20.08.2026 (Телеспутник) | F13: 3 | G13: 2 | H13: 2 | I13: 2 | J13: =IF(COUNT(F13:I13)=0,"",ROUND(((F13*Методика!$B$33+G13*Методика!$B$34+H13*Методика!$B$35+I13*Методика!$B$36)/3)*100,1)) -> 76.7 | K13: =IF(J13="","",INDEX(Методика!$C$42:$C$45,MATCH(J13,Методика!$A$42:$A$45,1))) -> Горячая тема | L13: На встрече в Минцифры «Сбер» предложил создать Совет по генеративной разработке ПО: методология агентной разработки, стандартизация, оценка экономического эффекта нейросетей в программировании, стандарты эффективности вычислительных мощностей. Участники — «Ростелеком», Т-банк, ВТБ, «Росатом», РЖД и др. Министр Шадаев поручил к концу года подготовить практические предложения по оценке экономической эффективности.
A14: 43 | B14: АМОР предложила компромисс в «реформе связи»: институт аварийного оператора | C14: Отраслевое событие (позиция ассоциации по реформе лицензирования связи) | D14: 12–20.08.2026 | E14: GR-дайджест 12–20.08.2026 (ComNews) | F14: 3 | G14: 2 | H14: 2 | I14: 3 | J14: =IF(COUNT(F14:I14)=0,"",ROUND(((F14*Методика!$B$33+G14*Методика!$B$34+H14*Методика!$B$35+I14*Методика!$B$36)/3)*100,1)) -> 83.3 | K14: =IF(J14="","",INDEX(Методика!$C$42:$C$45,MATCH(J14,Методика!$A$42:$A$45,1))) -> Горячая тема | L14: Ассоциация малых операторов связи регионов (АМОР) направила в Минцифры и Правительство альтернативу «реформе связи»: вместо передачи сетей операторов, лишившихся лицензии, системообразующему игроку — институт аварийного оператора. АМОР считает, что текущая версия реформы ведёт к монополизации рынка. Параллельно в ГД в рабочем порядке распространён законопроект о новой системе лицензирования связи (базовая/универсальная/генеральная лицензии, требования к уставному капиталу, СОРМ) — из мониторинга законодательства 17–21.08.

Sheet Методика
A1: Методика оценки влияния НПА и ранжирования отраслевых новостей
A3: Критерии оценки и веса (сумма весов = 100%) | B3: Вес | D3: Шкала (0–3 балла)
A4: К1. Применимость к деятельности GS Labs | B4: 0.25 | D4: 0 — не применимо · 1 — косвенно, общеотраслевой характер · 2 — применимо к части продуктов · 3 — прямое влияние на ключевые продукты/выручку
A5: К2. Юридическая сила / стадия принятия | B5: 0.15 | D5: 0 — информационный/зарубежный акт · 1 — законопроект внесён · 2 — принят в чтениях, готовится к подписанию · 3 — подписан/действует
A6: К3. Финансовое воздействие | B6: 0.2 | D6: 0 — отсутствует · 1 — незначительное · 2 — существенное (комплаенс-расходы, налоги, льготы) · 3 — критическое (прямое влияние на выручку/издержки)
A7: К4. Операционная сложность адаптации | B7: 0.15 | D7: 0 — действий не требуется · 1 — точечные изменения документов/процессов · 2 — изменения продуктов/инфраструктуры · 3 — перестройка ключевых процессов
A8: К5. Юридический и репутационный риск | B8: 0.15 | D8: 0 — ответственность не предусмотрена · 1 — незначительная административная · 2 — существенная административная/оборотная · 3 — уголовная/блокирующая деятельность
A9: К6. Срочность (время до применения) | B9: 0.1 | D9: 0 — свыше 12 мес. · 1 — 6–12 мес. · 2 — 1–6 мес. · 3 — менее 1 мес. или уже действует
A10: Сумма весов (должна быть 100%) | B10: =SUM(B4:B9) -> 1
A11: Формула итогового индекса влияния (ИВ)
A12: ИВ = [ (К1×вес1 + К2×вес2 + К3×вес3 + К4×вес4 + К5×вес5 + К6×вес6) / 3 ] × 100, округление до 0,1
A13: Шкала итогового индекса, категории и рекомендованные действия
A14: Мин. балл | C14: Категория | D14: Реакция системы
A15: 0 | C15: Незначительное | D15: Архивирование с пометкой «на заметку»; действие не требуется
A16: 25 | C16: Низкое | D16: Фиксация в реестре; переоценка при изменении стадии акта; пересмотр раз в квартал
A17: 50 | C17: Среднее | D17: Разбор в рамках планового цикла (2 недели); включение в квартальный обзор
A18: 75 | C18: Высокое | D18: Разбор профильным экспертом (3 раб. дня); согласование плана действий с руководством (1 неделя)
A19: 90 | C19: Критическое | D19: Немедленная эскалация руководству и юристу; план действий за 2 раб. дня; контроль еженедельно
A21: Столбцы A (мин. балл), B (веса) и вся шкала используются формулами листов реестра — изменять согласованно
A23: Флаги автоматической эскалации (ставить «Да» в столбце N реестра вручную)
A24: • Акт относит оборот ИИ, защиту конфиденциальной информации, деятельность ЦОД или доверенное ПО к стратегически значимым объектам
A25: • Акт вводит новую уголовную ответственность за генеративный ИИ/дипфейки, применимую к функциям GS Labs
A26: • Акт меняет критерии ИТ-аккредитации или условия налоговых/кадровых льгот для ИТ-компаний
A27: • Судебный акт формирует новый стандарт доказывания/ответственности по спорам о переработке ПО или коммерческой тайне
A28: • Санкция может привести к приостановке деятельности информационного ресурса/сервиса GS Labs
A31: Ранжирование отраслевых новостей (лист «Отраслевые новости»)
A32: Критерий | B32: Вес | D32: Шкала (0–3 балла)
A33: Н1. Актуальность события | B33: 0.3 | D33: 0 — архивное · 1 — старше месяца · 2 — текущий месяц · 3 — произошло/раскрыто на этой неделе, тема активно развивается
A34: Н2. Релевантность продуктам и бизнесу GS Labs | B34: 0.3 | D34: 0 — не связано · 1 — косвенно · 2 — затрагивает часть продуктов/процессов · 3 — прямое влияние на выручку, затраты или продуктовую стратегию
A35: Н3. Масштаб для отрасли | B35: 0.2 | D35: 0 — локальное · 1 — сегмент рынка · 2 — вся ИТ/ТВ-отрасль РФ · 3 — отрасль + смежные рынки/госполитика
A36: Н4. Динамика развития | B36: 0.2 | D36: 0 — статично · 1 — единичное событие · 2 — развивается, новые шаги ожидаются в 6–12 мес. · 3 — стремительно, события каждую неделю/месяц
A37: Сумма весов (должна быть 100%) | B37: =SUM(B33:B36) -> 1
A39: Индекс актуальности ИА = [ (Н1×вес1 + Н2×вес2 + Н3×вес3 + Н4×вес4) / 3 ] × 100, округление до 0,1
A41: Мин. балл | C41: Категория | D41: Реакция системы
A42: 0 | C42: Фон | D42: Архив; пересмотр не требуется
A43: 25 | C43: На заметку | D43: Краткая фиксация; пересмотр раз в квартал
A44: 50 | C44: Актуально | D44: Включить в еженедельный дайджест; мониторинг развития события
A45: 75 | C45: Горячая тема | D45: Разбор на неделе публикации; оценка влияния на планы компании

Sheet Источники
A1: Источники информации за период 03–28.08.2026
A2: Источники, использованные при обновлении реестра (03–25.08.2026); привязка к номерам карточек (сквозная нумерация).
A3: Источник (URL) | B3: Название источника | C3: К чему относится
A4: https://passwork.ru/blog/importozamieshchieniie-kii-v-2026/ | B4: Passwork (обзор), 21.06.2026 | C4: Карточка № 22 — ПП № 402, категорирование КИИ в связи
A5: https://www.interfax.ru/russia/1088934 | B5: Интерфакс, 12.05.2026 | C5: Карточки № 22, 27 — сроки перехода ЗО КИИ на российское ПО
A6: https://secpost.ru/mozhet-prevratitsya-v-formalnoe-importozameshhenie-na-bumage-minczifry-gotovit-predelnye-sroki-dlya-importozameshheniya-na-zo-kii | B6: SecPost, 12.05.2026 | C6: Карточка № 27 — оценки готовности отрасли (40–45%)
A7: https://www.pgplaw.ru/analytics-and-brochures/alerts/pravila-vedeniya-reestra-rossiyskogo-po/ | B7: Pepeliaev Group, 20.01.2026 | C7: Карточка № 23 — правила реестра ПО (ПП № 1937)
A8: https://acsour.com/tpost/a5vnh0hx01-novie-trebovaniya-k-po-v-reestre-mintsif | B8: Acsour, 06.03.2026 | C8: Карточка № 23 — этапы совместимости с доверенными ОС
A9: https://www.vedomosti.ru/technology/articles/2026/06/09/1204423-tehnologicheskii-sbor-zapustyat-s-dekabrya | B9: Ведомости, 09.06.2026 | C9: Карточка № 24 — техсбор, перенос на 01.12.2026, позиция GS Group
A10: https://www.interfax.ru/business/1094691 | B10: Интерфакс, 08.06.2026 | C10: Карточка № 24 — прогноз поступлений, этапность
A11: https://nalog-nalog.ru/nalogovye-izmeneniya-2026/tehnologicheskij-sbor-na-elektroniku-s-1-sentyabrya-2026-kto-za-chto-i-skolko-platit/ | B11: Налог-Налог, 03.07.2026 | C11: Карточка № 24 — перечень этапа 1 и ориентиры ставок
A12: https://telesputnik.ru/materials/gov/news/mincifry-predlozilo-pravila-upravleniya-m2m-sim-kartami-dlya-biznesa | B12: Телеспутник, 10.08.2026 | C12: Карточка № 25 — правила M2M SIM
A13: https://www.kommersant.ru/doc/8815085 | B13: Коммерсантъ, 14.07.2026 | C13: Карточка № 26 — законопроект о дипфейках
A14: https://ppt.ru/news/ugolovnaya-otvetstvennost/ispolzovanie-dipfeykov-priznayut-otyagchayushchim-obstoyatelstvom | B14: ППТ.ру, 15.07.2026 | C14: Карточка № 26 — отзывы Правительства и ВС РФ
... A39: https://regulation.gov.ru/projects#npa=165947 | B39: regulation.gov.ru, проект ID 165947 | C39: Карточка № 24 — финальный перечень и ставки техсбора не опубликованы

Sheet Ссылки мониторинга
A1: Каналы регулярного мониторинга
A2: Источники из исходного реестра; дополняйте по мере необходимости.
A3: Ссылка / канал | B3: Название | C3: Периодичность
A4: https://t.me/cit_gov | B4: Цифровые индустриальные технологии - дайджест | C4: Еженедельно
A5: https://t.me/rfrit | B5: РФРИТ | C5: Еженедельно
A6: https://t.me/grantsforbussines | B6: Гранты для ИТ | C6: Еженедельно
A7: https://t.me/cio_channel | B7: CIO: канал IT руководителей | C7: По мере новых публикаций
A8: https://t.me/rustorgpred | B8: Торгпред - тендеры и закупки | C8: Раз в неделю
A9: https://t.me/government_rus | B9: Правительство РФ - сводки | C9: Раз в неделю
A10: https://t.me/arperf | B10: АРПЭ - новости | C10: Еженедельно
A11: https://t.me/icipr | B11: ЦИПР - новости и анонсы мероприятий | C11: По мере новых публикаций
A12: Правовой комитет АРПП | B12: Дайджесты ИРИ и ЭБР | C12: Еженедельно (понедельник)
A13: https://t.me/arppsoft | B13: АРПП - новости | C13: Еженедельно
